aiosomecomfort/__init__.py
aiosomecomfort/device.py
aiosomecomfort/exceptions.py
aiosomecomfort/location.py
aiosomecomfort-0.0.34.dist-info/licenses/LICENSE
aiosomecomfort-0.0.34.dist-info/METADATA
aiosomecomfort-0.0.34.dist-info/WHEEL
aiosomecomfort-0.0.34.dist-info/top_level.txt
aiosomecomfort-0.0.34.dist-info/RECORD
