Metadata-Version: 2.4
Name: AIOSomecomfort
Version: 0.0.34
Summary: A client for Honeywell's US-based cloud devices
Home-page: https://github.com/mkmer/AIOSomecomfort
Download-URL: https://github.com/mkmer/AIOSomecomfort/archive/refs/tags/0.0.34.tar.gz
Author: Mike Kasper
Author-email: m_kasper@sbcglobal.net
License: MIT
Classifier: Development Status :: 4 - Beta
Classifier: Intended Audience :: Developers
Classifier: License :: OSI Approved :: MIT License
Classifier: Operating System :: OS Independent
Classifier: Programming Language :: Python
License-File: LICENSE
Requires-Dist: aiohttp>=3.8.0
Requires-Dist: prettytable
Dynamic: author
Dynamic: author-email
Dynamic: classifier
Dynamic: description
Dynamic: description-content-type
Dynamic: download-url
Dynamic: home-page
Dynamic: license
Dynamic: license-file
Dynamic: requires-dist
Dynamic: summary
